ncca/ngl/.ruff_cache/.gitignore
ncca/ngl/.ruff_cache/0.13.0/10564494386971134025
ncca/ngl/.ruff_cache/0.13.0/7783445477288392980
ncca/ngl/.ruff_cache/CACHEDIR.TAG
ncca/ngl/PrimData/NGLDebug.log
ncca/ngl/PrimData/Primitives.npz
ncca/ngl/PrimData/buddah.npy
ncca/ngl/PrimData/bunny.npy
ncca/ngl/PrimData/cube.npy
ncca/ngl/PrimData/dodecahedron.npy
ncca/ngl/PrimData/dragon.npy
ncca/ngl/PrimData/football.npy
ncca/ngl/PrimData/icosahedron.npy
ncca/ngl/PrimData/octahedron.npy
ncca/ngl/PrimData/pack_arrays.py
ncca/ngl/PrimData/teapot.npy
ncca/ngl/PrimData/tetrahedron.npy
ncca/ngl/PrimData/troll.npy
ncca/ngl/__init__.py
ncca/ngl/abstract_vao.py
ncca/ngl/base_mesh.py
ncca/ngl/base_mesh.pyi
ncca/ngl/bbox.py
ncca/ngl/bezier_curve.py
ncca/ngl/first_person_camera.py
ncca/ngl/image.py
ncca/ngl/log.py
ncca/ngl/mat2.py
ncca/ngl/mat3.py
ncca/ngl/mat4.py
ncca/ngl/multi_buffer_vao.py
ncca/ngl/obj.py
ncca/ngl/plane.py
ncca/ngl/prim_data.py
ncca/ngl/primitives.py
ncca/ngl/pyside_event_handling_mixin.py
ncca/ngl/quaternion.py
ncca/ngl/random.py
ncca/ngl/shader.py
ncca/ngl/shader_lib.py
ncca/ngl/shader_program.py
ncca/ngl/shaders/checker_fragment.glsl
ncca/ngl/shaders/checker_vertex.glsl
ncca/ngl/shaders/colour_fragment.glsl
ncca/ngl/shaders/colour_vertex.glsl
ncca/ngl/shaders/diffuse_fragment.glsl
ncca/ngl/shaders/diffuse_vertex.glsl
ncca/ngl/shaders/text_fragment.glsl
ncca/ngl/shaders/text_geometry.glsl
ncca/ngl/shaders/text_vertex.glsl
ncca/ngl/simple_index_vao.py
ncca/ngl/simple_vao.py
ncca/ngl/text.py
ncca/ngl/texture.py
ncca/ngl/transform.py
ncca/ngl/util.py
ncca/ngl/vao_factory.py
ncca/ngl/vec2.py
ncca/ngl/vec2_array.py
ncca/ngl/vec3.py
ncca/ngl/vec3_array.py
ncca/ngl/vec4.py
ncca/ngl/vec4_array.py
ncca/ngl/widgets/NGLDebug.log
ncca/ngl/widgets/__init__.py
ncca/ngl/widgets/__main__.py
ncca/ngl/widgets/glsl/phong.frag
ncca/ngl/widgets/glsl/phong.vert
ncca/ngl/widgets/glsl/picking.frag
ncca/ngl/widgets/glsl/picking.vert
ncca/ngl/widgets/lookatwidget.py
ncca/ngl/widgets/mat4widget.py
ncca_ngl-0.3.5.dist-info/WHEEL
ncca_ngl-0.3.5.dist-info/METADATA
ncca_ngl-0.3.5.dist-info/RECORD
