Metadata-Version: 2.3
Name: ncca-ngl
Version: 0.3.5
Summary: A Python version of the NGL graphics library.
Author: Jon Macey
Author-email: Jon Macey <jmacey@bournemouth.ac.uk>
License: Copyright 2024 Jon Macey
Requires-Dist: numpy>=2.3.3
Requires-Dist: pyopengl
Requires-Dist: pillow
Requires-Dist: glfw>=2.9.0
Requires-Dist: freetype-py>=2.5.1
Requires-Dist: pyside6>=6.9.2
Requires-Python: >=3.13
Project-URL: Homepage, https://github.com/NCCA/PyNGL
Project-URL: Issues, https://github.com/NCCA/PyNGL/issues
